{
  "posts": [
    {
      "id": 1,
      "title": "json-server",
      "author": "typicode"
    }
  ],
  "comments": [
    {
      "id": 1,
      "body": "some comment",
      "postId": 1
    }
  ],
  "profile": {
    "name": "typicode"
  },
  "Contenedores": [
    {
        "Id_Contenedor_Trasvaciado": 66,
        "Contenedor": "HLBU9268405p",
        "Estado": "RECONTEO",
        "Reconteo": true,
        "Origen": "China",
        "Validacion": "OnTime",
        "Destino": "Bogota",
        "Flete": "Activo"
    },
    {
        "Id_Contenedor_Trasvaciado": 81,
        "Contenedor": "TLLU8886041p",
        "Estado": "EN PROCESO",
        "Reconteo": false,
        "Origen": "China",
        "Validacion": "OnTime",
        "Destino": "Bogota",
        "Flete": "Activo"
    },
    {
        "Id_Contenedor_Trasvaciado": 64,
        "Contenedor": "HLBU1330418",
        "Estado": "EN PROCESO",
        "Reconteo": false,
        "Origen": "China",
        "Validacion": "OnTime",
        "Destino": "Bogota",
        "Flete": "Activo"
    },
    {
        "Id_Contenedor_Trasvaciado": 43,
        "Contenedor": "ONEU0306580",
        "Estado": "EN PROCESO",
        "Reconteo": false,
        "Origen": "China",
        "Validacion": "OnTime",
        "Destino": "Bogota",
        "Flete": "Activo"
    },
    {
        "Id_Contenedor_Trasvaciado": 44,
        "Contenedor": "MSKU8139425",
        "Estado": "EN PROCESO",
        "Reconteo": false,
        "Origen": "China",
        "Validacion": "OnTime",
        "Destino": "Bogota",
        "Flete": "Activo"
    },
    {
        "Id_Contenedor_Trasvaciado": 65,
        "Contenedor": "UACU8514111",
        "Estado": "EN PROCESO",
        "Reconteo": false,
        "Origen": "China",
        "Validacion": "OnTime",
        "Destino": "Bogota",
        "Flete": "Activo"
    },
    {
        "Id_Contenedor_Trasvaciado": 83,
        "Contenedor": "HLBU9775478",
        "Estado": "POR INICIAR",
        "Reconteo": false,
        "Origen": "China",
        "Validacion": "OnTime",
        "Destino": "Bogota",
        "Flete": "Activo"
    },
    {
        "Id_Contenedor_Trasvaciado": 69,
        "Contenedor": "HLBU9268405",
        "Estado": "POR INICIAR",
        "Reconteo": false,
        "Origen": "China",
        "Validacion": "OnTime",
        "Destino": "Bogota",
        "Flete": "Activo"
    },
    {
        "Id_Contenedor_Trasvaciado": 82,
        "Contenedor": "HLBU9517663",
        "Estado": "POR INICIAR",
        "Reconteo": false,
        "Origen": "China",
        "Validacion": "OnTime",
        "Destino": "Bogota",
        "Flete": "Activo"
    }
]
}